Workbook

Sheet Cover
A2: Zaara Royal Catering
A3: Zaara Royal Catering — Menu & Costing Sheet
A4: Menu, Item-wise Cost Breakdown & Profit Sheet
A6: What's in this workbook:
A7: 1) Item Cost Detail — the individual cost (৳) of every item in each package is listed here.
A8: 2) Package Summary — each package's sale price, total cost (added up automatically by formula), profit and profit margin (%).
A9: 3) Yellow cells (on the Item Cost Detail sheet) are editable — enter actual market prices there and the Package Summary sheet will update automatically.
A10: 4) All prices are in Bangladeshi Taka (৳) and are per head.
A12: Contact: Phone — 01XXX-XXXXXX | Address — enter your area name

Sheet Item Cost Detail
A1: Zaara Royal Catering — Item Cost Detail
A3: Category | B3: Package | C3: Item | D3: Item Cost (৳)
A4: Breakfast | B4: Classic Breakfast | C4: Paratha (2 pcs) | D4: 20
A5: Breakfast | B5: Classic Breakfast | C5: Vegetable Bhaji | D5: 10
A6: Breakfast | B6: Classic Breakfast | C6: Scrambled Egg | D6: 10
A7: Breakfast | B7: Classic Breakfast | C7: Chola Dal | D7: 10
A8: Breakfast | B8: Classic Breakfast | C8: Sweet | D8: 10
A9: Breakfast | B9: Classic Breakfast | C9: Black Tea | D9: 10
A10: Breakfast | B10: Premium Breakfast | C10: Luchi or Paratha | D10: 25
A11: Breakfast | B11: Premium Breakfast | C11: Aloo Dum | D11: 15
A12: Breakfast | B12: Premium Breakfast | C12: Egg Curry | D12: 15
A13: Breakfast | B13: Premium Breakfast | C13: Boot Dal | D13: 10
A14: Breakfast | B14: Premium Breakfast | C14: Semolina Halwa | D14: 15
A15: Breakfast | B15: Premium Breakfast | C15: Seasonal Fruit | D15: 10
... A148: House Party | B148: BBQ Night | C148: Dessert | D148: 10
A150: Yellow cells = editable item costs. Changes here update the Package Summary sheet automatically.

Sheet Package Summary
A1: Zaara Royal Catering — Package Summary
A3: Category | B3: Package | C3: Sale Price ৳ | D3: Total Cost ৳ (Formula) | E3: Profit ৳ | F3: Profit Margin % | G3: Notes
A4: Breakfast
A5: Breakfast | B5: Classic Breakfast | C5: 120 | D5: =SUMIFS('Item Cost Detail'!$D:$D,'Item Cost Detail'!$A:$A,$A5,'Item Cost Detail'!$B:$B,$B5) -> 70 | E5: =C5-D5 -> 50 | F5: =IF(C5=0,0,E5/C5) -> 0.41666667
A6: Breakfast | B6: Premium Breakfast | C6: 180 | D6: =SUMIFS('Item Cost Detail'!$D:$D,'Item Cost Detail'!$A:$A,$A6,'Item Cost Detail'!$B:$B,$B6) -> 105 | E6: =C6-D6 -> 75 | F6: =IF(C6=0,0,E6/C6) -> 0.41666667
A7: Breakfast | B7: Royal Breakfast | C7: 250 | D7: =SUMIFS('Item Cost Detail'!$D:$D,'Item Cost Detail'!$A:$A,$A7,'Item Cost Detail'!$B:$B,$B7) -> 145 | E7: =C7-D7 -> 105 | F7: =IF(C7=0,0,E7/C7) -> 0.42
A8: Lunch
A9: Lunch | B9: Standard | C9: 250 | D9: =SUMIFS('Item Cost Detail'!$D:$D,'Item Cost Detail'!$A:$A,$A9,'Item Cost Detail'!$B:$B,$B9) -> 145 | E9: =C9-D9 -> 105 | F9: =IF(C9=0,0,E9/C9) -> 0.42
A10: Lunch | B10: Premium | C10: 350 | D10: =SUMIFS('Item Cost Detail'!$D:$D,'Item Cost Detail'!$A:$A,$A10,'Item Cost Detail'!$B:$B,$B10) -> 205 | E10: =C10-D10 -> 145 | F10: =IF(C10=0,0,E10/C10) -> 0.41428571
A11: Lunch | B11: Royal Kacchi | C11: 500 | D11: =SUMIFS('Item Cost Detail'!$D:$D,'Item Cost Detail'!$A:$A,$A11,'Item Cost Detail'!$B:$B,$B11) -> 300 | E11: =C11-D11 -> 200 | F11: =IF(C11=0,0,E11/C11) -> 0.4 | G11: Mutton Kacchi carries an extra ৳80/head
A12: Dinner
A13: Dinner | B13: Standard | C13: 280 | D13: =SUMIFS('Item Cost Detail'!$D:$D,'Item Cost Detail'!$A:$A,$A13,'Item Cost Detail'!$B:$B,$B13) -> 165 | E13: =C13-D13 -> 115 | F13: =IF(C13=0,0,E13/C13) -> 0.41071429
A14: Dinner | B14: Premium | C14: 400 | D14: =SUMIFS('Item Cost Detail'!$D:$D,'Item Cost Detail'!$A:$A,$A14,'Item Cost Detail'!$B:$B,$B14) -> 235 | E14: =C14-D14 -> 165 | F14: =IF(C14=0,0,E14/C14) -> 0.4125
A15: Dinner | B15: Royal Dinner | C15: 550 | D15: =SUMIFS('Item Cost Detail'!$D:$D,'Item Cost Detail'!$A:$A,$A15,'Item Cost Detail'!$B:$B,$B15) -> 320 | E15: =C15-D15 -> 230 | F15: =IF(C15=0,0,E15/C15) -> 0.41818182
A16: Milad & Doa Mahfil
A17: Milad & Doa Mahfil | B17: Tabarak Package | C17: 150 | D17: =SUMIFS('Item Cost Detail'!$D:$D,'Item Cost Detail'!$A:$A,$A17,'Item Cost Detail'!$B:$B,$B17) -> 85 | E17: =C17-D17 -> 65 | F17: =IF(C17=0,0,E17/C17) -> 0.43333333
A18: Milad & Doa Mahfil | B18: Standard Doa Mahfil | C18: 220 | D18: =SUMIFS('Item Cost Detail'!$D:$D,'Item Cost Detail'!$A:$A,$A18,'Item Cost Detail'!$B:$B,$B18) -> 130 | E18: =C18-D18 -> 90 | F18: =IF(C18=0,0,E18/C18) -> 0.40909091
A19: Milad & Doa Mahfil | B19: Full Meal Package | C19: 320 | D19: =SUMIFS('Item Cost Detail'!$D:$D,'Item Cost Detail'!$A:$A,$A19,'Item Cost Detail'!$B:$B,$B19) -> 190 | E19: =C19-D19 -> 130 | F19: =IF(C19=0,0,E19/C19) -> 0.40625 | G19: Includes packaging & distribution support
A20: Corporate Program
A21: Corporate Program | B21: Snacks / Tea Break Package | C21: 80 | D21: =SUMIFS('Item Cost Detail'!$D:$D,'Item Cost Detail'!$A:$A,$A21,'Item Cost Detail'!$B:$B,$B21) -> 45 | E21: =C21-D21 -> 35 | F21: =IF(C21=0,0,E21/C21) -> 0.4375 | G21: Ideal for morning or afternoon meeting breaks
A22: Corporate Program | B22: Box Lunch | C22: 220 | D22: =SUMIFS('Item Cost Detail'!$D:$D,'Item Cost Detail'!$A:$A,$A22,'Item Cost Detail'!$B:$B,$B22) -> 130 | E22: =C22-D22 -> 90 | F22: =IF(C22=0,0,E22/C22) -> 0.40909091
A23: Corporate Program | B23: Standard Buffet | C23: 380 | D23: =SUMIFS('Item Cost Detail'!$D:$D,'Item Cost Detail'!$A:$A,$A23,'Item Cost Detail'!$B:$B,$B23) -> 220 | E23: =C23-D23 -> 160 | F23: =IF(C23=0,0,E23/C23) -> 0.42105263 | G23: Minimum 40 guests
A24: Corporate Program | B24: Executive Buffet | C24: 550 | D24: =SUMIFS('Item Cost Detail'!$D:$D,'Item Cost Detail'!$A:$A,$A24,'Item Cost Detail'!$B:$B,$B24) -> 320 | E24: =C24-D24 -> 230 | F24: =IF(C24=0,0,E24/C24) -> 0.41818182 | G24: Includes waiter service & cutlery
A25: House Party
A26: House Party | B26: Snacks Party | C26: 200 | D26: =SUMIFS('Item Cost Detail'!$D:$D,'Item Cost Detail'!$A:$A,$A26,'Item Cost Detail'!$B:$B,$B26) -> 115 | E26: =C26-D26 -> 85 | F26: =IF(C26=0,0,E26/C26) -> 0.425
A27: House Party | B27: Full Dinner Party | C27: 420 | D27: =SUMIFS('Item Cost Detail'!$D:$D,'Item Cost Detail'!$A:$A,$A27,'Item Cost Detail'!$B:$B,$B27) -> 245 | E27: =C27-D27 -> 175 | F27: =IF(C27=0,0,E27/C27) -> 0.41666667
A28: House Party | B28: BBQ Night | C28: 650 | D28: =SUMIFS('Item Cost Detail'!$D:$D,'Item Cost Detail'!$A:$A,$A28,'Item Cost Detail'!$B:$B,$B28) -> 380 | E28: =C28-D28 -> 270 | F28: =IF(C28=0,0,E28/C28) -> 0.41538462 | G28: Outdoor setup & live chef service available (extra charges apply)
B30: Overall Average — All Packages | C30: =AVERAGE(C5,C6,C7,C9,C10,C11,C13,C14,C15,C17,C18,C19,C21,C22,C23,C24,C26,C27,C28) -> 319.47368 | D30: =AVERAGE(D5,D6,D7,D9,D10,D11,D13,D14,D15,D17,D18,D19,D21,D22,D23,D24,D26,D27,D28) -> 186.84211 | E30: =AVERAGE(E5,E6,E7,E9,E10,E11,E13,E14,E15,E17,E18,E19,E21,E22,E23,E24,E26,E27,E28) -> 132.63158 | F30: =AVERAGE(F5,F6,F7,F9,F10,F11,F13,F14,F15,F17,F18,F19,F21,F22,F23,F24,F26,F27,F28) -> 0.4168719 | G30: Average sale price / cost / profit / profit margin
A32: Blue numbers = user-entered sale prices (editable). Black numbers = calculated automatically by formula — do not edit.

Sheet Sheet1
A1: Breakfast
A3: Package | B3: Item-wise Cost Breakdown | C3: Sale Price | D3: Cost | E3: Profit | F3: Margin
A4: Classic Breakfast | B4: Paratha (2 pcs) 20 + Vegetable Bhaji 10 + Scrambled Egg 10 + Chola Dal 10 + Sweet 10 + Black Tea 10 = 70 | C4: ৳120 | D4: ৳70 | E4: ৳50 | F4: 0.42
A5: Premium Breakfast | B5: Luchi/Paratha 25 + Aloo Dum 15 + Egg Curry 15 + Boot Dal 10 + Semolina Halwa 15 + Seasonal Fruit 10 + Doi-Chira (Yogurt & Flattened Rice) 10 + Tea/Coffee 5 = 105 | C5: ৳180 | D5: ৳105 | E5: ৳75 | F5: 0.42
A6: Royal Breakfast | B6: Bhuna Khichuri 30 + Beef Bhuna 50 + Egg Curry 15 + Fried Eggplant 10 + Borhani 15 + Salad 5 + Jilapi/Sweet 15 + Tea/Coffee 5 = 145 | C6: ৳250 | D6: ৳145 | E6: ৳105 | F6: 0.42
A8: Lunch
A10: Package | B10: Item-wise Cost Breakdown | C10: Sale Price | D10: Cost | E10: Profit | F10: Margin
A11: Standard | B11: White Rice 20 + Chicken Curry 75 + Masoor Dal 15 + Mixed Vegetables 15 + Aloo Bhorta (Mashed Potato) 10 + Salad 5 + Pickle 5 = 145 | C11: ৳250 | D11: ৳145 | E11: ৳105 | F11: 0.42
A12: Premium | B12: Rice/Polao 25 + Chicken Roast 50 + Beef Bhuna 60 + Fried Rui Fish 35 + Dal 10 + Vegetables 10 + Salad 5 + Sweet Yogurt 5 + Paan-Supari 5 = 205 | C12: ৳350 | D12: ৳205 | E12: ৳145 | F12: 0.41
A13: Royal Kacchi | B13: Kacchi Biryani 205 + Borhani 25 + Salad 10 + Egg 15 + Fried Eggplant 10 + Shahi Zarda 20 + Sweet 10 + Paan-Supari 5 = 300 | C13: ৳500 | D13: ৳300 | E13: ৳200 | F13: 0.4
A15: Dinner
A17: Package | B17: Item-wise Cost Breakdown | C17: Sale Price | D17: Cost | E17: Profit | F17: Margin
A18: Standard | B18: Polao 25 + Chicken Rezala 90 + Dal 15 + Vegetables 15 + Salad 5 + Pickle 5 + Sweet 10 = 165 | C18: ৳280 | D18: ৳165 | E18: ৳115 | F18: 0.41
A19: Premium | B19: Polao 30 + Chicken Roast 55 + Beef Rezala 70 + Hilsa/Rui Fish 35 + Dal 10 + Vegetables 10 + Salad 5 + Borhani 15 + Firni 5 = 235 | C19: ৳400 | D19: ৳235 | E19: ৳165 | F19: 0.41
A20: Royal Dinner | B20: Morog Polao/Kacchi 75 + Beef Kala Bhuna 75 + Mutton Rezala 85 + Fried Fish 35 + Dal 10 + Borhani 15 + Salad 5 + Shahi Tukra 15 + Fruit Platter 5 = 320 | C20: ৳550 | D20: ৳320 | E20: ৳230 | F20: 0.42
A22: Milad & Doa Mahfil
A24: Package | B24: Item-wise Cost Breakdown | C24: Sale Price | D24: Cost | E24: Profit | F24: Margin
A25: Tabarak Package | B25: Sweet Polao/Zarda 25 + Beef 45 + Chickpeas 5 + Dates 5 + Water 5 = 85 | C25: ৳150 | D25: ৳85 | E25: ৳65 | F25: 0.43
A26: Standard Doa Mahfil | B26: Rice/Polao 20 + Chicken Curry 70 + Dal 10 + Vegetables 10 + Salad 5 + Pickle 5 + Sweet 5 + Water 5 = 130 | C26: ৳220 | D26: ৳130 | E26: ৳90 | F26: 0.41
A27: Full Meal Package | B27: Polao 25 + Chicken Roast 55 + Beef Bhuna 60 + Dal 10 + Vegetables 10 + Salad 5 + Egg 10 + Zarda 5 + Sweet 5 + Water 5 = 190 | C27: ৳320 | D27: ৳190 | E27: ৳130 | F27: 0.41
A29: Corporate Program
A31: Package | B31: Item-wise Cost Breakdown | C31: Sale Price | D31: Cost | E31: Profit | F31: Margin
A32: Snacks / Tea Break | B32: Samosa 10 + Singara 10 + Chicken Pakora 15 + Biscuits 5 + Tea/Coffee 3 + Water 2 = 45 | C32: ৳80 | D32: ৳45 | E32: ৳35 | F32: 0.44
A33: Box Lunch | B33: Polao/Rice 20 + Chicken Curry 80 + Dal 10 + Vegetables 10 + Salad 5 + Mineral Water 5 = 130 | C33: ৳220 | D33: ৳130 | E33: ৳90 | F33: 0.41
A34: Standard Buffet | B34: Rice & Polao 25 + 2 Chicken/Beef Dishes 110 + Fish 30 + Dal 10 + Vegetables 10 + Salad Bar 10 + Dessert 15 + Soft Drink 10 = 220 | C34: ৳380 | D34: ৳220 | E34: ৳160 | F34: 0.42
A35: Executive Buffet | B35: Kacchi/Biryani 90 + Roast 70 + Kebab Station 60 + Fish 35 + Salad Bar 15 + Soup 15 + Dessert 15 + Beverages 15 + Tea/Coffee Corner 5 = 320 | C35: ৳550 | D35: ৳320 | E35: ৳230 | F35: 0.42
A37: House Party
A39: Package | B39: Item-wise Cost Breakdown | C39: Sale Price | D39: Cost | E39: Profit | F39: Margin
A40: Snacks Party | B40: Chicken Fry 35 + Shawarma/Roll 30 + Fuchka/Chotpoti 15 + French Fries 15 + Spring Roll 15 + Soft Drink 5 = 115 | C40: ৳200 | D40: ৳115 | E40: ৳85 | F40: 0.43
A41: Full Dinner Party | B41: Polao 30 + Chicken Roast 60 + Beef Bhuna 75 + Fish Fry 40 + Dal 10 + Vegetables 10 + Salad 5 + Borhani 10 + Dessert 5 = 245 | C41: ৳420 | D41: ৳245 | E41: ৳175 | F41: 0.42
A42: BBQ Night | B42: Chicken/Beef BBQ 180 + Grilled Kebab 110 + Naan 25 + Salad Bar 20 + Dip Sauce 10 + Soft Drink 25 + Dessert 10 = 380 | C42: ৳650 | D42: ৳380 | E42: ৳270 | F42: 0.42
